pysmartapp/__init__.py
pysmartapp/config.py
pysmartapp/const.py
pysmartapp/dispatch.py
pysmartapp/errors.py
pysmartapp/event.py
pysmartapp/install.py
pysmartapp/oauthcallback.py
pysmartapp/ping.py
pysmartapp/request.py
pysmartapp/smartapp.py
pysmartapp/uninstall.py
pysmartapp/update.py
pysmartapp/utilities.py
pysmartapp-0.3.5.dist-info/LICENSE
pysmartapp-0.3.5.dist-info/METADATA
pysmartapp-0.3.5.dist-info/WHEEL
pysmartapp-0.3.5.dist-info/top_level.txt
pysmartapp-0.3.5.dist-info/RECORD
