Metadata-Version: 2.1
Name: pysmartapp
Version: 0.3.5
Summary: A python library for building a SmartThings SmartApp
Home-page: https://github.com/andrewsayre/pysmartapp
Author: Andrew Sayre
Author-email: andrew@sayre.net
License: MIT
Keywords: smartthings,smartapp
Platform: any
Classifier: Development Status :: 4 - Beta
Classifier: Intended Audience :: Developers
Classifier: License :: OSI Approved :: MIT License
Classifier: Operating System :: OS Independent
Classifier: Topic :: Software Development :: Libraries
Classifier: Topic :: Home Automation
Classifier: Programming Language :: Python :: 3.10
Classifier: Programming Language :: Python :: 3.11
License-File: LICENSE
Requires-Dist: httpsig (<2.0.0,>=1.3.0)
